{
  "dataset_name": "orders_base_final",
  "grain_definition": "1 row = 1 order",
  "n_rows": 99441,
  "n_cols": 52,
  "columns": [
    "order_id",
    "customer_id",
    "order_status",
    "order_purchase_timestamp",
    "order_approved_at",
    "order_delivered_carrier_date",
    "order_delivered_customer_date",
    "order_estimated_delivery_date",
    "customer_unique_id",
    "customer_city",
    "customer_state",
    "customer_zip_code_prefix",
    "customer_geo_lat_mean",
    "customer_geo_lng_mean",
    "item_count",
    "unique_products",
    "unique_sellers",
    "price_sum",
    "freight_value_sum",
    "price_mean",
    "main_category",
    "seller_city_mode",
    "seller_state_mode",
    "seller_geo_lat_mean",
    "seller_geo_lng_mean",
    "payment_sequential_max",
    "payment_installments_max",
    "payment_value_sum",
    "payment_type_mode",
    "review_count",
    "review_score",
    "review_comment_message",
    "review_comment_length",
    "has_comment",
    "review_response_hours",
    "approval_time_hours",
    "purchase_to_carrier_days",
    "delivery_time_days",
    "shipping_time_days",
    "delivery_delay_days",
    "basket_value",
    "purchase_year",
    "purchase_month",
    "purchase_day",
    "purchase_hour",
    "purchase_dayofweek",
    "purchase_month_period",
    "is_late_delivery",
    "review_label",
    "time_issue_approval_before_purchase",
    "time_issue_carrier_before_purchase",
    "time_issue_customer_before_carrier"
  ],
  "dtypes": {
    "order_id": "object",
    "customer_id": "object",
    "order_status": "object",
    "order_purchase_timestamp": "datetime64[ns]",
    "order_approved_at": "datetime64[ns]",
    "order_delivered_carrier_date": "datetime64[ns]",
    "order_delivered_customer_date": "datetime64[ns]",
    "order_estimated_delivery_date": "datetime64[ns]",
    "customer_unique_id": "object",
    "customer_city": "object",
    "customer_state": "object",
    "customer_zip_code_prefix": "Int64",
    "customer_geo_lat_mean": "float64",
    "customer_geo_lng_mean": "float64",
    "item_count": "float64",
    "unique_products": "float64",
    "unique_sellers": "float64",
    "price_sum": "float64",
    "freight_value_sum": "float64",
    "price_mean": "float64",
    "main_category": "object",
    "seller_city_mode": "object",
    "seller_state_mode": "object",
    "seller_geo_lat_mean": "float64",
    "seller_geo_lng_mean": "float64",
    "payment_sequential_max": "float64",
    "payment_installments_max": "float64",
    "payment_value_sum": "float64",
    "payment_type_mode": "object",
    "review_count": "float64",
    "review_score": "float64",
    "review_comment_message": "object",
    "review_comment_length": "float64",
    "has_comment": "Int64",
    "review_response_hours": "float64",
    "approval_time_hours": "float64",
    "purchase_to_carrier_days": "float64",
    "delivery_time_days": "float64",
    "shipping_time_days": "float64",
    "delivery_delay_days": "float64",
    "basket_value": "float64",
    "purchase_year": "int32",
    "purchase_month": "int32",
    "purchase_day": "int32",
    "purchase_hour": "int32",
    "purchase_dayofweek": "int32",
    "purchase_month_period": "object",
    "is_late_delivery": "Int64",
    "review_label": "Int64",
    "time_issue_approval_before_purchase": "bool",
    "time_issue_carrier_before_purchase": "bool",
    "time_issue_customer_before_carrier": "bool"
  }
}